[
	{
		"id": "1",
		"dateTime": "24 October 2024/09:34 PM",
		"sizeCount": "349",
		"balance": "230000",
		"name": "Anonymous Gifting",
		"goal": "Gifts for annonymous people",
		"status": "Active"
	},
	{
		"id": "2",
		"dateTime": "24 October 2024/09:34 PM",
		"sizeCount": "349",
		"balance": "230000",
		"name": "Anonymous Gifting",
		"goal": "Gifts for annonymous people",
		"status": "Active"
	},
	{
		"id": "3",
		"dateTime": "24 October 2024/09:34 PM",
		"sizeCount": "349",
		"balance": "230000",
		"name": "Anonymous Gifting",
		"goal": "Gifts for annonymous people",
		"status": "Inactive"
	},
	{
		"id": "4",
		"dateTime": "24 October 2024/09:34 PM",
		"sizeCount": "349",
		"balance": "230000",
		"name": "Anonymous Gifting",
		"goal": "Gifts for annonymous people",
		"status": "Active"
	},
	{
		"id": "5",
		"dateTime": "24 October 2024/09:34 PM",
		"sizeCount": "349",
		"balance": "230000",
		"name": "Anonymous Gifting",
		"goal": "Gifts for annonymous people",
		"status": "Active"
	},
	{
		"id": "6",
		"dateTime": "24 October 2024/09:34 PM",
		"sizeCount": "349",
		"balance": "230000",
		"name": "Anonymous Gifting",
		"goal": "Gifts for annonymous people",
		"status": "Inactive"
	},
	{
		"id": "7",
		"dateTime": "24 October 2024/09:34 PM",
		"sizeCount": "349",
		"balance": "230000",
		"name": "Anonymous Gifting",
		"goal": "Gifts for annonymous people",
		"status": "Active"
	},
	{
		"id": "8",
		"dateTime": "24 October 2024/09:34 PM",
		"sizeCount": "349",
		"balance": "230000",
		"name": "Anonymous Gifting",
		"goal": "Gifts for annonymous people",
		"status": "Active"
	},
	{
		"id": "9",
		"dateTime": "24 October 2024/09:34 PM",
		"sizeCount": "349",
		"balance": "230000",
		"name": "Anonymous Gifting",
		"goal": "Gifts for annonymous people",
		"status": "Active"
	},
	{
		"id": "10",
		"dateTime": "24 October 2024/09:34 PM",
		"sizeCount": "349",
		"balance": "230000",
		"name": "Anonymous Gifting",
		"goal": "Gifts for annonymous people",
		"status": "Active"
	},
	{
		"id": "11",
		"dateTime": "24 October 2024/09:34 PM",
		"sizeCount": "349",
		"balance": "230000",
		"name": "Anonymous Gifting",
		"goal": "Gifts for annonymous people",
		"status": "Inactive"
	},
	{
		"id": "12",
		"dateTime": "24 October 2024/09:34 PM",
		"sizeCount": "349",
		"balance": "230000",
		"name": "Anonymous Gifting",
		"goal": "Gifts for annonymous people",
		"status": "Active"
	},
	{
		"id": "13",
		"dateTime": "24 October 2024/09:34 PM",
		"sizeCount": "349",
		"balance": "230000",
		"name": "Anonymous Gifting",
		"goal": "Gifts for annonymous people",
		"status": "Active"
	},
	{
		"id": "14",
		"dateTime": "24 October 2024/09:34 PM",
		"sizeCount": "349",
		"balance": "230000",
		"name": "Anonymous Gifting",
		"goal": "Gifts for annonymous people",
		"status": "Active"
	},
	{
		"id": "15",
		"dateTime": "24 October 2024/09:34 PM",
		"sizeCount": "349",
		"balance": "230000",
		"name": "Anonymous Gifting",
		"goal": "Gifts for annonymous people",
		"status": "Active"
	},
	{
		"id": "16",
		"dateTime": "24 October 2024/09:34 PM",
		"sizeCount": "349",
		"balance": "230000",
		"name": "Anonymous Gifting",
		"goal": "Gifts for annonymous people",
		"status": "Active"
	},
	{
		"id": "17",
		"dateTime": "24 October 2024/09:34 PM",
		"sizeCount": "349",
		"balance": "230000",
		"name": "Anonymous Gifting",
		"goal": "Gifts for annonymous people",
		"status": "Active"
	},
	{
		"id": "18",
		"dateTime": "24 October 2024/09:34 PM",
		"sizeCount": "349",
		"balance": "230000",
		"name": "Anonymous Gifting",
		"goal": "Gifts for annonymous people",
		"status": "Active"
	},
	{
		"id": "19",
		"dateTime": "24 October 2024/09:34 PM",
		"sizeCount": "349",
		"balance": "230000",
		"name": "Anonymous Gifting",
		"goal": "Gifts for annonymous people",
		"status": "Active"
	},
	{
		"id": "20",
		"dateTime": "24 October 2024/09:34 PM",
		"sizeCount": "349",
		"balance": "230000",
		"name": "Anonymous Gifting",
		"goal": "Gifts for annonymous people",
		"status": "Active"
	},
	{
		"id": "21",
		"dateTime": "24 October 2024/09:34 PM",
		"sizeCount": "349",
		"balance": "230000",
		"name": "Anonymous Gifting",
		"goal": "Gifts for annonymous people",
		"status": "Active"
	},
	{
		"id": "22",
		"dateTime": "24 October 2024/09:34 PM",
		"sizeCount": "349",
		"balance": "230000",
		"name": "Anonymous Gifting",
		"goal": "Gifts for annonymous people",
		"status": "Active"
	},
	{
		"id": "23",
		"dateTime": "24 October 2024/09:34 PM",
		"sizeCount": "349",
		"balance": "230000",
		"name": "Anonymous Gifting",
		"goal": "Gifts for annonymous people",
		"status": "Inactive"
	},
	{
		"id": "24",
		"dateTime": "24 October 2024/09:34 PM",
		"sizeCount": "349",
		"balance": "230000",
		"name": "Anonymous Gifting",
		"goal": "Gifts for annonymous people",
		"status": "Active"
	},
	{
		"id": "25",
		"dateTime": "24 October 2024/09:34 PM",
		"sizeCount": "349",
		"balance": "230000",
		"name": "Anonymous Gifting",
		"goal": "Gifts for annonymous people",
		"status": "Active"
	},
	{
		"id": "26",
		"dateTime": "24 October 2024/09:34 PM",
		"sizeCount": "349",
		"balance": "230000",
		"name": "Anonymous Gifting",
		"goal": "Gifts for annonymous people",
		"status": "Active"
	},
	{
		"id": "27",
		"dateTime": "24 October 2024/09:34 PM",
		"sizeCount": "349",
		"balance": "230000",
		"name": "Anonymous Gifting",
		"goal": "Gifts for annonymous people",
		"status": "Active"
	},
	{
		"id": "28",
		"dateTime": "24 October 2024/09:34 PM",
		"sizeCount": "349",
		"balance": "230000",
		"name": "Anonymous Gifting",
		"goal": "Gifts for annonymous people",
		"status": "Active"
	},
	{
		"id": "29",
		"dateTime": "24 October 2024/09:34 PM",
		"sizeCount": "349",
		"balance": "230000",
		"name": "Anonymous Gifting",
		"goal": "Gifts for annonymous people",
		"status": "Active"
	},
	{
		"id": "30",
		"dateTime": "24 October 2024/09:34 PM",
		"sizeCount": "349",
		"balance": "230000",
		"name": "Anonymous Gifting",
		"goal": "Gifts for annonymous people",
		"status": "Active"
	},
	{
		"id": "31",
		"dateTime": "24 October 2024/09:34 PM",
		"sizeCount": "349",
		"balance": "230000",
		"name": "Anonymous Gifting",
		"goal": "Gifts for annonymous people",
		"status": "Active"
	},
	{
		"id": "32",
		"dateTime": "24 October 2024/09:34 PM",
		"sizeCount": "349",
		"balance": "230000",
		"name": "Anonymous Gifting",
		"goal": "Gifts for annonymous people",
		"status": "Active"
	},
	{
		"id": "33",
		"dateTime": "24 October 2024/09:34 PM",
		"sizeCount": "349",
		"balance": "230000",
		"name": "Anonymous Gifting",
		"goal": "Gifts for annonymous people",
		"status": "Active"
	},
	{
		"id": "34",
		"dateTime": "24 October 2024/09:34 PM",
		"sizeCount": "349",
		"balance": "230000",
		"name": "Anonymous Gifting",
		"goal": "Gifts for annonymous people",
		"status": "Active"
	},
	{
		"id": "35",
		"dateTime": "24 October 2024/09:34 PM",
		"sizeCount": "349",
		"balance": "230000",
		"name": "Anonymous Gifting",
		"goal": "Gifts for annonymous people",
		"status": "Inactive"
	}
]
